[{"_id":2700,"BookId":2700,"Wisdom":"طُوبَى لِمَنْ ذَكَرَ الْمَعَادَ فَاسْتَكْثَرَ مِنَ الزَّادِ","enWisdom":"Blessed is the one who remembers the [Day of] Resurrection and thus increases his provisions","Qsm":"1","Bab":"6","Fsl":"40","Topic":"217","Source":"1","fav":0,"lastcheckdate":""},{"_id":2701,"BookId":2701,"Wisdom":"عَجِبْتُ لِمَنْ عَرَفَ أَنَّهُ مُنْتَقِلٌ عَنْ دُنْيَاهُ كَيْفَ لَا يُحْسِنُ التَّزَوُّدَ لِأُخْرَاهُ","enWisdom":"I am amazed at the one who knows that he will surely be moving away from his world, how can he not acquire a goodly provision for his Hereafter?!","Qsm":"1","Bab":"6","Fsl":"40","Topic":"217","Source":"1","fav":0,"lastcheckdate":""},{"_id":2702,"BookId":2702,"Wisdom":"لِيَكُنْ زَادُكَ التَّقْوَى","enWisdom":"Let your provision be God-wariness","Qsm":"1","Bab":"6","Fsl":"40","Topic":"217","Source":"1","fav":0,"lastcheckdate":""},{"_id":2703,"BookId":2703,"Wisdom":"مَنْ أَيْقَنَ بِالنُّقْلَةِ تَأَهَّبَ لِلرَّحِيلِ","enWisdom":"One who is certain of the [eventual] departure [from this world] prepares for the journey","Qsm":"1","Bab":"6","Fsl":"40","Topic":"217","Source":"1","fav":0,"lastcheckdate":""},{"_id":2704,"BookId":2704,"Wisdom":"مَنْ وُفِّقَ لِرَشَادِهِ تَزَوُّدَ لِمَعَادِهِ","enWisdom":"One who is successful in his [attaining] rectitude acquires provisions for his Hereafter","Qsm":"1","Bab":"6","Fsl":"40","Topic":"217","Source":"1","fav":0,"lastcheckdate":""},{"_id":2705,"BookId":2705,"Wisdom":"مَنْ أَيْقَنَ بِالْمَعَادِ اسْتَكْثَرَ مِنَ الزَّادِ","enWisdom":"Blessed is the one who remembers the [Day of] Resurrection and thus increases his provisions","Qsm":"1","Bab":"6","Fsl":"40","Topic":"217","Source":"1","fav":0,"lastcheckdate":""},{"_id":2706,"BookId":2706,"Wisdom":"إِنَّ مِنَ الْفَسَادِ إِضَاعَةَ الزَّادِ","enWisdom":"Verily the wasting of provisions is from corruption","Qsm":"1","Bab":"6","Fsl":"40","Topic":"217","Source":"1","fav":0,"lastcheckdate":""},{"_id":2707,"BookId":2707,"Wisdom":"مِنَ الْفَسَادِ إِضَاعَةُ الزَّادِ","enWisdom":"Verily the wasting of provisions is from corruption","Qsm":"1","Bab":"6","Fsl":"40","Topic":"217","Source":"1","fav":0,"lastcheckdate":""},{"_id":2708,"BookId":2708,"Wisdom":"مِنَ الْعَقْلِ التَّزَوُّدُ لِيَوْمِ الْمَعَادِ","enWisdom":"Accumulating provisions for the Day of Return is from intelligence","Qsm":"1","Bab":"6","Fsl":"40","Topic":"217","Source":"1","fav":0,"lastcheckdate":""},{"_id":2709,"BookId":2709,"Wisdom":"الْآخِرَةُ دَارُ مُسْتَقَرِّكُمْ فَجَهِّزُوا إِلَيْهَا مَا يَبْقَى لَكُمْ","enWisdom":"The Hereafter is the abode of your permanent stay, so prepare for it that which will be lasting for you","Qsm":"1","Bab":"6","Fsl":"40","Topic":"217","Source":"1","fav":0,"lastcheckdate":""},{"_id":2710,"BookId":2710,"Wisdom":"ارْتَدِ لِنَفْسِكَ قَبْلَ يَوْمِ نُزُولِكَ وَوَطِّ [وَطِّئِ‏] الْمَنْزِلَ قَبْلَ حُلُولِكَ","enWisdom":"Select your abode for yourself before the day of your landing and prepare your dwelling before your arrival","Qsm":"1","Bab":"6","Fsl":"40","Topic":"217","Source":"1","fav":0,"lastcheckdate":""},{"_id":2711,"BookId":2711,"Wisdom":"أَلَا مُتَزَوِّدٌ لِآخِرَتِهِ قَبْلَ أُزُوفِ رِحْلَتِهِ","enWisdom":"Is there nobody who has prepared the provisions for his Hereafter before the coming of [the hour of] his departure?","Qsm":"1","Bab":"6","Fsl":"40","Topic":"217","Source":"1","fav":0,"lastcheckdate":""},{"_id":2712,"BookId":2712,"Wisdom":"أَلَا وَقَدْ أُمِرْتُمْ بِالظَّعْنِ وَدُلِلْتُمْ عَلَى الزَّادِ فَتَزَوَّدُوا مِنَ الدُّنْيَا مَا تَحُوزُونَ بِهِ أَنْفُسَكُمْ غَداً","enWisdom":"Indeed, you have been commanded to decamp and have been shown your provision [for the journey], so take from this world the provisions that you can hold on to (or that will protect you) tomorrow","Qsm":"1","Bab":"6","Fsl":"40","Topic":"217","Source":"1","fav":0,"lastcheckdate":""},{"_id":2713,"BookId":2713,"Wisdom":"إِنَّ أَمَامَكَ طَرِيقاً ذَا مَسَافَةٍ بَعِيدَةٍ وَمَشَقَّةٍ شَدِيدَةٍ وَلَا غِنَى بِكَ مِنْ حُسْنِ الِارْتِيَادِ وَقَدْرِ بَلَاغِكَ مِنَ الزَّادِ","enWisdom":"Verily in front of you there is a path that covers a long distance, and severe hardships, and you cannot do without good exploration and acquiring the necessary amount of provisions","Qsm":"1","Bab":"6","Fsl":"40","Topic":"217","Source":"1","fav":0,"lastcheckdate":""},{"_id":2714,"BookId":2714,"Wisdom":"إِنَّ الْعَاقِلَ مَنْ نَظَرَ فِي يَوْمِهِ لِغَدِهِ وَسَعَى فِي فَكَاكِ نَفْسِهِ وَعَمِلَ لِمَا لَا بُدَّ لَهُ مِنْهُ وَلَا مَحِيصَ لَهُ عَنْهُ","enWisdom":"Verily the intelligent person is one who looks in his today for his tomorrow, and strives to unshackle his soul, and works for that which must come to pass and which cannot be escaped","Qsm":"1","Bab":"6","Fsl":"40","Topic":"217","Source":"1","fav":0,"lastcheckdate":""},{"_id":2715,"BookId":2715,"Wisdom":"إِنَّ الدُّنْيَا لَمْ تُخْلَقْ لَكُمْ دَارَ مُقَامٍ وَلَا مَحَلَّ قَرَارٍ وَإِنَّمَا جُعِلَتْ لَكُمْ مَجَازاً لِتَزَوَّدُوا مِنْهَا الْأَعْمَالَ الصَّالِحَةَ لِدَارِ الْقَرَارِ فَكُونُوا مِنْهَا عَلَى أَوْفَازٍ وَلَا تَخْدَعَنَّكُمْ مِنْهَا الْعَاجِلَةُ وَلَا تَغُرَّنَّكُمْ فِيهَا الْفِتْنَةُ","enWisdom":"This world was neither created for you as a permanent abode nor as a place to settle, rather it has only been made as a passage for you so that you may acquire from it the provisions of good deeds for the abode of [permanent] settlementTherefore be alert and do not let its temporary pleasures deceive you or its temptations beguile you","Qsm":"1","Bab":"6","Fsl":"40","Topic":"217","Source":"1","fav":0,"lastcheckdate":""},{"_id":2716,"BookId":2716,"Wisdom":"إِنْ رَغِبْتُمْ فِي الْفَوْزِ وَكَرَامَةِ الْآخِرَةِ فَخُذُوا فِي الْفَنَاءِ لِلْبَقَاءِ","enWisdom":"If you desire success and honor in the Hereafter, then take from the perishing [life of this world] for the everlasting [life of the Hereafter]","Qsm":"1","Bab":"6","Fsl":"40","Topic":"217","Source":"1","fav":0,"lastcheckdate":""},{"_id":2717,"BookId":2717,"Wisdom":"إِنِّي آمُرُكُمْ بِحُسْنِ الِاسْتِعْدَادِ وَالْإِكْثَارِ مِنَ الزَّادِ لِيَوْمِ تَقْدَمُونَ عَلَى مَا تُقَدِّمُونَ وَتَنْدَمُونَ عَلَى مَا تُخَلِّفُونَ وَتُجْزَوْنَ بِمَا كُنْتُمْ تُسْلِفُونَ","enWisdom":"I enjoin you to be well prepared and increase your provisions for the day when you will meet with what you have sent forth and regret what you have left behind, and will be rewarded for what you had forwarded [in advance]","Qsm":"1","Bab":"6","Fsl":"40","Topic":"217","Source":"1","fav":0,"lastcheckdate":""},{"_id":2718,"BookId":2718,"Wisdom":"إِنَّمَا الدُّنْيَا دَارُ مَمَرٍّ وَالْآخِرَةُ دَارُ مُسْتَقَرٍّ فَخُذُوا مِنْ مَمَرِّكُمْ لِمُسْتَقَرِّكُمْ وَلَا تَهْتِكُوا أَسْتَارَكُمْ عِنْدَ مَنْ يَعْلَمُ أَسْرَارَكُمْ","enWisdom":"Indeed this world is only the abode of passage and the Hereafter is the abode of [permanent] residenceSo take [provisions] from the abode of passage for the abode of residence and do not tear your veils in front of the one who knows your secrets","Qsm":"1","Bab":"6","Fsl":"40","Topic":"217","Source":"1","fav":0,"lastcheckdate":""},{"_id":2719,"BookId":2719,"Wisdom":"إِنَّمَا لَكَ مِنْ مَالِكَ مَا قَدَّمْتَهُ لِآخِرَتِكَ وَمَا أَخَّرْتَهُ فَلِلْوَارِثِ","enWisdom":"Verily only the wealth which you send ahead for your Hereafter is yours, while that which you leave behind belongs to your heirs","Qsm":"1","Bab":"6","Fsl":"40","Topic":"217","Source":"1","fav":0,"lastcheckdate":""},{"_id":2720,"BookId":2720,"Wisdom":"تَزَوَّدُوا مِنْ أَيَّامِ الْفَنَاءِ لِلْبَقَاءِ فَقَدْ دُلِلْتُمْ عَلَى الزَّادِ وَأُمِرْتُمْ بِالظَّعْنِ وَحُثِثْتُمْ عَلَى الْمَسِيرِ","enWisdom":"Take provisions from the days of transience for the everlasting [abode], for you have been shown your provision and commanded to decamp and [have been] driven upon the course","Qsm":"1","Bab":"6","Fsl":"40","Topic":"217","Source":"1","fav":0,"lastcheckdate":""},{"_id":2721,"BookId":2721,"Wisdom":"تَزَوَّدُوا مِنَ الدُّنْيَا مَا تَحُوزُونَ بِهِ أَنْفُسَكُمْ غَداً وَخُذُوا مِنَ الْفَنَاءِ لِلْبَقَاءِ","enWisdom":"Take from this world the provisions that you can hold on to (or that will protect you) tomorrow and take from the transient for the everlasting","Qsm":"1","Bab":"6","Fsl":"40","Topic":"217","Source":"1","fav":0,"lastcheckdate":""},{"_id":2722,"BookId":2722,"Wisdom":"تُوبُوا مِنَ الْغَفْلَةِ وَتَنَبَّهُوا مِنَ الرَّقْدَةِ وَتَأَهَّبُوا لِلنُّقْلَةِ وَتَزَوَّدُوا لِلرِّحْلَةِ","enWisdom":"Return from negligence, awake from slumber, prepare yourself for the move and gather provisions for the journey","Qsm":"1","Bab":"6","Fsl":"40","Topic":"217","Source":"1","fav":0,"lastcheckdate":""},{"_id":2723,"BookId":2723,"Wisdom":"خُذْ مِنْ نَفْسِكَ لِنَفْسِكَ وَتَزَوَّدْ مِنْ يَوْمِكَ لِغَدِكَ وَاغْتَنِمْ عَفْوَ الزَّمَانِ وَانْتَهِزْ فُرْصَةَ الْإِمْكَانِ","enWisdom":"Take [good deeds] from yourself for your soul [in the Hereafter], gather provisions today for your tomorrow, benefit from the slumber (or respite) of time and seize the opportunity [to do good while you can]","Qsm":"1","Bab":"6","Fsl":"40","Topic":"217","Source":"1","fav":0,"lastcheckdate":""},{"_id":2724,"BookId":2724,"Wisdom":"خُذْ مِمَّا لَا يَبْقَى لَكَ لِمَا يَبْقَى لَكَ وَلَا يُفَارِقُكَ","enWisdom":"Take from that which will not last for you for that which will last for you and will not separate from you","Qsm":"1","Bab":"6","Fsl":"40","Topic":"217","Source":"1","fav":0,"lastcheckdate":""},{"_id":2725,"BookId":2725,"Wisdom":"طُوبَى لِمَنْ أَحْسَنَ إِلَى الْعِبَادِ وَتَزَوَّدَ لِلْمَعَادِ","enWisdom":"Blessed is the one who does good to the servants [of Allah] and prepares provisions for the Hereafter","Qsm":"1","Bab":"6","Fsl":"40","Topic":"217","Source":"1","fav":0,"lastcheckdate":""},{"_id":2726,"BookId":2726,"Wisdom":"طُوبَى لِمَنْ قَدَّمَ خَالِصاً وَعَمِلَ صَالِحاً وَاكْتَسَبَ مَذْخُوراً وَاجْتَنَبَ مَحْذُوراً","enWisdom":"Blessed is he who proceeds with sincerity, acts with righteousness, acquires the reserves [for the Hereafter] and eschews [the disobedience of Allah] cautiously","Qsm":"1","Bab":"6","Fsl":"40","Topic":"217","Source":"1","fav":0,"lastcheckdate":""},{"_id":2727,"BookId":2727,"Wisdom":"عَزِيمَةُ الْكَيِّسِ وَجِدُّهُ لِإِصْلَاحِ الْمَعَادِ وَالِاسْتِكْثَارِ مِنَ الزَّادِ","enWisdom":"The determination and effort of the sagacious one is for the improvement of his Hereafter and for acquiring more provisions [for it]","Qsm":"1","Bab":"6","Fsl":"40","Topic":"217","Source":"1","fav":0,"lastcheckdate":""},{"_id":2728,"BookId":2728,"Wisdom":"مَا قَدَّمْتَ مِنْ دُنْيَاكَ فَلِنَفْسِكَ وَمَا أَخَّرْتَ مِنْهَا فَلِلْعَدُوِّ","enWisdom":"That which you send forth from this world is for your own benefit and that which you leave behind from it is for your enemy","Qsm":"1","Bab":"6","Fsl":"40","Topic":"217","Source":"1","fav":0,"lastcheckdate":""},{"_id":2729,"BookId":2729,"Wisdom":"مَا أَعْظَمَ الْمُصِيبَةَ فِي الدُّنْيَا مَعَ عِظَمِ الْفَاقَةِ غَداً","enWisdom":"How great is the hardship in this world when accompanied by the severe indigence of tomorrow [iethe Hereafter]!","Qsm":"1","Bab":"6","Fsl":"40","Topic":"217","Source":"1","fav":0,"lastcheckdate":""},{"_id":2730,"BookId":2730,"Wisdom":"يَنْبَغِي لِلْعَاقِلِ أَنْ يُقَدِّمَ لِآخِرَتِهِ وَيَعْمُرَ دَارَ إِقَامَتِهِ","enWisdom":"It behoves the intelligent one to make arrangements for his Hereafter and to develop [and build] the abode of his permanent residence","Qsm":"1","Bab":"6","Fsl":"40","Topic":"217","Source":"1","fav":0,"lastcheckdate":""},{"_id":2731,"BookId":2731,"Wisdom":"اسْتَحِقُّوا مِنَ اللَّهِ مَا أَعَدَّ لَكُمْ بِالتَّنَجُّزِ لِصِدْقِ مِيعَادِهِ وَالْحَذَرِ مِنْ هَوْلِ مَعَادِهِ","enWisdom":"Become deserving of what Allah has prepared for you [in the Hereafter] by seeking the fulfillment of His true promise and being wary of the horror of His reckoning","Qsm":"1","Bab":"6","Fsl":"40","Topic":"217","Source":"1","fav":0,"lastcheckdate":""},{"_id":2732,"BookId":2732,"Wisdom":"إِنَّ الْمَرْءَ عَلَى مَا قَدَّمَ قَادِمٌ وَعَلَى مَا خَلَّفَ نَادِمٌ","enWisdom":"Verily a person comes to that which he has sent forward [of his good deeds] and regrets [about] that which he has left behind","Qsm":"1","Bab":"6","Fsl":"40","Topic":"217","Source":"1","fav":0,"lastcheckdate":""},{"_id":2733,"BookId":2733,"Wisdom":"رَحِمَ اللَّهُ امْرَءاً بَادَرَ الْأَجَلَ وَأَحْسَنَ الْعَمَلَ لِدَارِ إِقَامَتِهِ وَمَحَلِّ كَرَامَتِهِ","enWisdom":"May Allah have mercy upon the person who anticipates death and performs good deeds for the abode of his [permanent] residence and the place of his dignity","Qsm":"1","Bab":"6","Fsl":"40","Topic":"217","Source":"1","fav":0,"lastcheckdate":""},{"_id":2734,"BookId":2734,"Wisdom":"رَحِمَ اللَّهُ امْرَءاً قَصَّرَ الْأَمَلَ وَبَادَرَ الْأَجَلَ وَاغْتَنَمَ الْمَهَلَ وَتَزَوَّدَ مِنَ الْعَمَلِ","enWisdom":"May Allah have mercy on the man who shortens his hopes, anticipates death, makes good use of his time and takes with him the provisions of [good] deeds","Qsm":"1","Bab":"6","Fsl":"40","Topic":"217","Source":"1","fav":0,"lastcheckdate":""},{"_id":2735,"BookId":2735,"Wisdom":"رَحِمَ اللَّهُ امْرَءاً أَخَذَ مِنْ حَيَاةٍ لِمَوْتٍ وَمِنْ فَنَاءٍ لِبَقَاءٍ وَمِنْ ذَاهِبٍ لِدَائِمٍ","enWisdom":"May Allah have mercy on the person who takes from [his] life for [his] death, from the transitory for the everlasting and from the perishing for the permanent","Qsm":"1","Bab":"6","Fsl":"40","Topic":"217","Source":"1","fav":0,"lastcheckdate":""},{"_id":2736,"BookId":2736,"Wisdom":"زَادُ الْمَرْءِ [الْمُؤْمِنِ‏] إِلَى الْآخِرَةِ الْوَرَعُ وَالتُّقَى","enWisdom":"The provision of a person for the Hereafter is piety and God-wariness","Qsm":"1","Bab":"6","Fsl":"40","Topic":"217","Source":"1","fav":0,"lastcheckdate":""},{"_id":2737,"BookId":2737,"Wisdom":"قَدِّمُوا بَعْضاً يَكُنْ لَكُمْ وَلَا تُخَلِّفُوا كُلًّا فَيَكُونَ عَلَيْكُمْ","enWisdom":"Send forth some [of your wealth] as it will be [beneficial] for you [in the Hereafter], and do not leave all of it behind as this will become a burden for you","Qsm":"1","Bab":"6","Fsl":"40","Topic":"217","Source":"1","fav":0,"lastcheckdate":""},{"_id":2738,"BookId":2738,"Wisdom":"رُبَّ سَلَفٍ عَادَ خَلَفاً","enWisdom":"Many a thing that has been sent ahead (or has been pillaged) returns back [as it was before]","Qsm":"1","Bab":"6","Fsl":"40","Topic":"217","Source":"1","fav":0,"lastcheckdate":""},{"_id":2739,"BookId":2739,"Wisdom":"قَدِّمْ إِحْسَانَكَ تَغْنَمْ","enWisdom":"Send your good turn ahead [for the Hereafter] and you will benefit","Qsm":"1","Bab":"6","Fsl":"40","Topic":"217","Source":"1","fav":0,"lastcheckdate":""},{"_id":2740,"BookId":2740,"Wisdom":"مَنْ قَدَّمَ خَيْراً وَجَدَهُ","enWisdom":"One who sends forth a good deed will find it [in the Hereafter]","Qsm":"1","Bab":"6","Fsl":"40","Topic":"217","Source":"1","fav":0,"lastcheckdate":""}]