[{"_id":7197,"BookId":7197,"Wisdom":"الْأَمَلُ خَوَّانٌ","enWisdom":"Hope is treacherous","Qsm":"3","Bab":"12","Fsl":"83","Topic":"519","Source":"1","fav":0,"lastcheckdate":""},{"_id":7198,"BookId":7198,"Wisdom":"الْأَمَانِيُّ شِيمَةُ الْحَمْقَى","enWisdom":"False aspiration is the trait of fools","Qsm":"3","Bab":"12","Fsl":"83","Topic":"519","Source":"1","fav":0,"lastcheckdate":""},{"_id":7199,"BookId":7199,"Wisdom":"الْآمَالُ غُرُورُ الْحَمْقَى","enWisdom":"Hopes are the delusions of the foolish","Qsm":"3","Bab":"12","Fsl":"83","Topic":"519","Source":"1","fav":0,"lastcheckdate":""},{"_id":7200,"BookId":7200,"Wisdom":"الْأَمَانِيُّ بَضَائِعُ النَّوْكَى","enWisdom":"Aspirations are the wares of the unintelligent","Qsm":"3","Bab":"12","Fsl":"83","Topic":"519","Source":"1","fav":0,"lastcheckdate":""},{"_id":7201,"BookId":7201,"Wisdom":"الْأَمَانِيُّ هِمَّةُ الرِّجَالِ [الْجُهَّالِ‏]","enWisdom":"Aspirations are incentives for men","Qsm":"3","Bab":"12","Fsl":"83","Topic":"519","Source":"1","fav":0,"lastcheckdate":""},{"_id":7202,"BookId":7202,"Wisdom":"الْآمَالُ لَا تَنْتَهِي","enWisdom":"Hopes never end","Qsm":"3","Bab":"12","Fsl":"83","Topic":"519","Source":"1","fav":0,"lastcheckdate":""},{"_id":7203,"BookId":7203,"Wisdom":"الْكَيِّسُ مَنْ قَصَّرَ آمَالَهُ","enWisdom":"The sagacious person is one who shortens his hopes","Qsm":"3","Bab":"12","Fsl":"83","Topic":"519","Source":"1","fav":0,"lastcheckdate":""},{"_id":7204,"BookId":7204,"Wisdom":"الْأَمَلُ لَا غَايَةَ لَهُ","enWisdom":"There is no end to hope","Qsm":"3","Bab":"12","Fsl":"83","Topic":"519","Source":"1","fav":0,"lastcheckdate":""},{"_id":7205,"BookId":7205,"Wisdom":"الْأَمَلُ رَفِيقٌ مُونِسٌ","enWisdom":"Hope is an intimate companion","Qsm":"3","Bab":"12","Fsl":"83","Topic":"519","Source":"1","fav":0,"lastcheckdate":""},{"_id":7206,"BookId":7206,"Wisdom":"الْأَمَلُ سُلْطَانُ الشَّيَاطِينِ عَلَى قُلُوبِ الْغَافِلِينَ","enWisdom":"Hope is the dominion of devils over hearts of the negligent","Qsm":"3","Bab":"12","Fsl":"83","Topic":"519","Source":"1","fav":0,"lastcheckdate":""},{"_id":7207,"BookId":7207,"Wisdom":"الْأَمَلُ كَالسَّرَابِ يَغُرُّ مَنْ رَآهُ وَيُخْلِفُ مَنْ رَجَاهُ","enWisdom":"Hope is like a mirage, it deceives the one who sees it and disheartens the one who looks forward to it","Qsm":"3","Bab":"12","Fsl":"83","Topic":"519","Source":"1","fav":0,"lastcheckdate":""},{"_id":7208,"BookId":7208,"Wisdom":"احْذَرُوا الْأَمَلَ الْمَغْلُوبَ وَالنَّعِيمَ الْمَسْلُوبَ","enWisdom":"Be cautious of dashed hopes and seized blessings","Qsm":"3","Bab":"12","Fsl":"83","Topic":"519","Source":"1","fav":0,"lastcheckdate":""},{"_id":7209,"BookId":7209,"Wisdom":"إِيَّاكَ وَالِاتِّكَالَ عَلَى الْمُنَى فَإِنَّهَا بَضَائِعُ النَّوْكَى","enWisdom":"Be cautious not to depend on hopes, for they are the wares of the unintelligent","Qsm":"3","Bab":"12","Fsl":"83","Topic":"519","Source":"1","fav":0,"lastcheckdate":""},{"_id":7210,"BookId":7210,"Wisdom":"إِيَّاكَ وَالثِّقَةَ بِالْآمَالِ فَإِنَّهَا مِنْ شِيَمِ الْحَمْقَى","enWisdom":"Beware of relying on [your] hopes, for this is the trait of fools","Qsm":"3","Bab":"12","Fsl":"83","Topic":"519","Source":"1","fav":0,"lastcheckdate":""},{"_id":7211,"BookId":7211,"Wisdom":"أَبْعَدُ شَيْ‏ءٍ الْأَمَلُ","enWisdom":"The farthest thing is hope","Qsm":"3","Bab":"12","Fsl":"83","Topic":"519","Source":"1","fav":0,"lastcheckdate":""},{"_id":7212,"BookId":7212,"Wisdom":"أَشْرَفُ الْغِنَى تَرْكُ الْمُنَى","enWisdom":"The most honourable wealth is abandoning [false] aspirations","Qsm":"3","Bab":"12","Fsl":"83","Topic":"519","Source":"1","fav":0,"lastcheckdate":""},{"_id":7213,"BookId":7213,"Wisdom":"أَنْفَعُ الدَّوَاءِ تَرْكُ الْمُنَى","enWisdom":"The most beneficial cure is abandoning [false] aspirations","Qsm":"3","Bab":"12","Fsl":"83","Topic":"519","Source":"1","fav":0,"lastcheckdate":""},{"_id":7214,"BookId":7214,"Wisdom":"أَطْوَلُ النَّاسِ أَمَلًا أَسْوَؤُهُمْ عَمَلًا","enWisdom":"Those who have the longest hopes are the ones whose deeds are the worst","Qsm":"3","Bab":"12","Fsl":"83","Topic":"519","Source":"1","fav":0,"lastcheckdate":""},{"_id":7215,"BookId":7215,"Wisdom":"أَكْثَرُ النَّاسِ أَمَلًا أَقَلُّهُمْ لِلْمَوْتِ ذِكْراً","enWisdom":"Those who have the most [false] hopes are the ones who remember death the least","Qsm":"3","Bab":"12","Fsl":"83","Topic":"519","Source":"1","fav":0,"lastcheckdate":""},{"_id":7216,"BookId":7216,"Wisdom":"إِنَّ اللَّهَ سُبْحَانَهُ لَيُبْغِضُ الطَّوِيلَ الْأَمَلِ السَّيِّئَ الْعَمَلِ","enWisdom":"Verily Allah, the Glorified, hates the one who has long hopes and performs evil actions","Qsm":"3","Bab":"12","Fsl":"83","Topic":"519","Source":"1","fav":0,"lastcheckdate":""},{"_id":7217,"BookId":7217,"Wisdom":"رُبَّ أُمْنِيَّةٍ تَحْتَ مَنِيَّةٍ","enWisdom":"Many an aspiration may lie beneath death","Qsm":"3","Bab":"12","Fsl":"83","Topic":"519","Source":"1","fav":0,"lastcheckdate":""},{"_id":7218,"BookId":7218,"Wisdom":"رَغْبَتُكَ فِي الْمُسْتَحِيلِ جَهْلٌ","enWisdom":"You desire for the unachievable is [a sign of] ignorance","Qsm":"3","Bab":"12","Fsl":"83","Topic":"519","Source":"1","fav":0,"lastcheckdate":""},{"_id":7219,"BookId":7219,"Wisdom":"شَرُّ الْفَقْرِ [الفقير] الْمُنَى","enWisdom":"The worst poverty is [false] aspiration","Qsm":"3","Bab":"12","Fsl":"83","Topic":"519","Source":"1","fav":0,"lastcheckdate":""},{"_id":7220,"BookId":7220,"Wisdom":"شَرُّ النَّاسِ الطَّوِيلُ الْأَمَلِ السَّيِّئُ الْعَمَلِ","enWisdom":"The worst person is he who has lengthy aspirations and does evil deeds","Qsm":"3","Bab":"12","Fsl":"83","Topic":"519","Source":"1","fav":0,"lastcheckdate":""},{"_id":7221,"BookId":7221,"Wisdom":"كَمْ مِنْ آمِلٍ خَائِبٍ وَغَائِبٍ غَيْرِ آئِبٍ","enWisdom":"Many [of those] who hope get disappointed, and many a traveller fails to return","Qsm":"3","Bab":"12","Fsl":"83","Topic":"519","Source":"1","fav":0,"lastcheckdate":""},{"_id":7222,"BookId":7222,"Wisdom":"كَمْ مِنْ مُؤَمِّلٍ مَا لَا يُدْرِكُهُ","enWisdom":"Many a person hopes for what he never achieves","Qsm":"3","Bab":"12","Fsl":"83","Topic":"519","Source":"1","fav":0,"lastcheckdate":""},{"_id":7223,"BookId":7223,"Wisdom":"كَذَبَ مَنِ ادَّعَى الْإِيمَانَ وَهُوَ مَشْغُوفٌ مِنَ الدُّنْيَا بِخُدَعِ الْأَمَانِيِّ وَزُورِ الْمَلَاهِي","enWisdom":"    He who claims to have faith yet is infatuated by misleading aspirations and false amusements of this world, has lied","Qsm":"3","Bab":"12","Fsl":"83","Topic":"519","Source":"1","fav":0,"lastcheckdate":""},{"_id":7224,"BookId":7224,"Wisdom":"مَنِ اتَّكَلَ عَلَى الْأَمَانِيِّ مَاتَ دُونَ أَمَلِهِ","enWisdom":"One who relies on his aspirations dies without [realizing] his hopes","Qsm":"3","Bab":"12","Fsl":"83","Topic":"519","Source":"1","fav":0,"lastcheckdate":""},{"_id":7225,"BookId":7225,"Wisdom":"مَنْ أَمَّلَ مَا لَا يُمْكِنُ طَالَ تَرَقُّبُهُ","enWisdom":"One who hopes for that which is not possible, his anticipation becomes long","Qsm":"3","Bab":"12","Fsl":"83","Topic":"519","Source":"1","fav":0,"lastcheckdate":""},{"_id":7226,"BookId":7226,"Wisdom":"مِنَ الْحُمْقِ الِاتِّكَالُ عَلَى الْأَمَلِ","enWisdom":"It is foolishness to depending on [one’s] hope","Qsm":"3","Bab":"12","Fsl":"83","Topic":"519","Source":"1","fav":0,"lastcheckdate":""},{"_id":7227,"BookId":7227,"Wisdom":"مَا عَقَلَ مَنْ أَطَالَ أَمَلَهُ","enWisdom":"One who lengthens his aspirations is not intelligent","Qsm":"3","Bab":"12","Fsl":"83","Topic":"519","Source":"1","fav":0,"lastcheckdate":""},{"_id":7228,"BookId":7228,"Wisdom":"لَا يَطُولَنَّ عَلَيْكُمُ الْأَمَدُ وَلَا يَغُرَّنَّكُمُ الْأَمَلُ فَإِنَّ الْأَمَلَ لَيْسَ مِنَ الدِّينِ فِي شَيْ‏ءٍ","enWisdom":"Do not consider your stay in this world to be long, and do not let your hopes deceive you, for indeed hopes are not part of religion in any way","Qsm":"3","Bab":"12","Fsl":"83","Topic":"519","Source":"1","fav":0,"lastcheckdate":""},{"_id":7229,"BookId":7229,"Wisdom":"لَا تَفِي الْأَمَانِيُّ لِمَنْ عَوَّلَ عَلَيْهَا","enWisdom":"Aspirations are not loyal to those who rely on them","Qsm":"3","Bab":"12","Fsl":"83","Topic":"519","Source":"1","fav":0,"lastcheckdate":""}]