[{"_id":7311,"BookId":7311,"Wisdom":"الِارْتِقَاءُ إِلَى الْفَضَائِلِ صَعْبٌ مُنْجٍ [منجي‏]","enWisdom":"Ascending towards virtues is a hardship that saves","Qsm":"3","Bab":"13","Fsl":"84","Topic":"525","Source":"1","fav":0,"lastcheckdate":""},{"_id":7312,"BookId":7312,"Wisdom":"الْكَرَمُ حُسْنُ السَّجِيَّةِ وَاجْتِنَابُ الدَّنِيَّةِ","enWisdom":"Being noble-minded means having a good character and eschewing lowly traits","Qsm":"3","Bab":"13","Fsl":"84","Topic":"525","Source":"1","fav":0,"lastcheckdate":""},{"_id":7313,"BookId":7313,"Wisdom":"الْفَضِيلَةُ بِحُسْنِ الْكَمَالِ وَمَكَارِمِ الْأَفْعَالِ لَا بِكَثْرَةِ الْمَالِ وَجَلَالَةِ الْأَعْمَالِ","enWisdom":"Merit is [acquired] by perfection [of character] and noble deeds, not through excessive wealth and eminent feats","Qsm":"3","Bab":"13","Fsl":"84","Topic":"525","Source":"1","fav":0,"lastcheckdate":""},{"_id":7314,"BookId":7314,"Wisdom":"أَكْرِهْ نَفْسَكَ عَلَى الْفَضَائِلِ فَإِنَّ الرَّذَائِلَ أَنْتَ مَطْبُوعٌ عَلَيْهَا","enWisdom":"Compel yourself to [acquire] virtues, for indeed you have a natural propensity for vices","Qsm":"3","Bab":"13","Fsl":"84","Topic":"525","Source":"1","fav":0,"lastcheckdate":""},{"_id":7315,"BookId":7315,"Wisdom":"أَقْوَى الْوَسَائِلِ حُسْنُ الْفَضَائِلِ","enWisdom":"The strongest means [of gaining success in this world and the next] is having excellent [qualities and] merits","Qsm":"3","Bab":"13","Fsl":"84","Topic":"525","Source":"1","fav":0,"lastcheckdate":""},{"_id":7316,"BookId":7316,"Wisdom":"إِنَّكُمْ إِلَى مَكَارِمِ الْأَفْعَالِ أَحْوَجُ مِنْكُمْ إِلَى جَمْعِ الْأَمْوَالِ","enWisdom":"Verily you are more in need of honourable deeds than you are of eloquent words","Qsm":"3","Bab":"13","Fsl":"84","Topic":"525","Source":"1","fav":0,"lastcheckdate":""},{"_id":7317,"BookId":7317,"Wisdom":"إِذَا رَغِبْتَ فِي الْمَكَارِمِ فَاجْتَنِبِ الْمَحَارِمَ","enWisdom":"When you desire to acquire noble traits then keep away from the forbidden","Qsm":"3","Bab":"13","Fsl":"84","Topic":"525","Source":"1","fav":0,"lastcheckdate":""},{"_id":7318,"BookId":7318,"Wisdom":"إِذَا كَانَ فِي الرَّجُلِ خَلَّةٌ رَائِقَةٌ فَانْتَظِرْ مِنْهُ أَخَوَاتِهَا","enWisdom":"When there is an admirable quality in a man, then expect from him other such qualities","Qsm":"3","Bab":"13","Fsl":"84","Topic":"525","Source":"1","fav":0,"lastcheckdate":""},{"_id":7319,"BookId":7319,"Wisdom":"إِذَا لَمْ تَنْفَعِ الْكَرَامَةُ فَالْإِهَانَةُ أَحْزَمُ وَإِذَا لَمْ يَنْجَعِ السَّوْطُ فَالسَّيْفُ أَحْسَمُ","enWisdom":"When [showing] respect is of no benefit then humiliation is firmer; when the whip is not successful then the sword is sharper","Qsm":"3","Bab":"13","Fsl":"84","Topic":"525","Source":"1","fav":0,"lastcheckdate":""},{"_id":7320,"BookId":7320,"Wisdom":"إِذَا كَانَتْ مَحَاسِنُ الرَّجُلِ أَكْثَرَ مِنْ مَسَاوِيهِ فَذَلِكَ الْكَامِلُ [التَّكَامُلُ‏] وَإِذَا كَانَ مُتَسَاوِيَ الْمَحَاسِنِ وَالْمَسَاوِي فَذَلِكَ الْمُتَمَاسِكُ وَإِنْ زَادَتْ مَسَاوِيهِ عَلَى مَحَاسِنِهِ فَذَلِكَ الْهَالِكُ","enWisdom":"When the virtues of a man are more than his vices, then that [person] is ideal, and when his virtues and vices are equal then he has protected himself [from destruction], but if his vices are more than his virtues then he is doomed","Qsm":"3","Bab":"13","Fsl":"84","Topic":"525","Source":"1","fav":0,"lastcheckdate":""},{"_id":7321,"BookId":7321,"Wisdom":"بِحُسْنِ الْأَفْعَالِ يَحْسُنُ الثَّنَاءُ","enWisdom":"Through virtuous deeds, praise becomes worthy","Qsm":"3","Bab":"13","Fsl":"84","Topic":"525","Source":"1","fav":0,"lastcheckdate":""},{"_id":7322,"BookId":7322,"Wisdom":"بِاكْتِسَابِ الْفَضَائِلِ يُكْبَتُ الْمُعَادِي","enWisdom":"Through the gaining of merits the enemy is subdued","Qsm":"3","Bab":"13","Fsl":"84","Topic":"525","Source":"1","fav":0,"lastcheckdate":""},{"_id":7323,"BookId":7323,"Wisdom":"تَحَلَّوْا بِالْأَخْذِ بِالْفَضْلِ وَالْكَفِّ عَنِ الْبَغْيِ وَالْعَمَلِ بِالْحَقِّ وَالْإِنْصَافِ مِنَ النَّفْسِ وَاجْتِنَابِ الْفَسَادِ وَإِصْلَاحِ الْمَعَادِ","enWisdom":"Adorn yourselves by taking up kindness, stopping transgression, acting upon the truth, being just and impartial, keeping away from corruption and improving your Hereafter","Qsm":"3","Bab":"13","Fsl":"84","Topic":"525","Source":"1","fav":0,"lastcheckdate":""},{"_id":7324,"BookId":7324,"Wisdom":"تَنَافَسُوا فِي الْأَخْلَاقِ الرَّغِيبَةِ وَالْأَحْلَامِ الْعَظِيمَةِ وَالْأَخْطَارِ الْجَلِيلَةِ يَعْظُمُ لَكُمُ الْجَزَاءُ","enWisdom":"Compete in acquiring [a] desirable character, great forbearance and lofty ideas, [and] your reward will become great","Qsm":"3","Bab":"13","Fsl":"84","Topic":"525","Source":"1","fav":0,"lastcheckdate":""},{"_id":7325,"BookId":7325,"Wisdom":"ثَابِرُوا عَلَى اقْتِنَاءِ الْمَكَارِمِ وَتَحَمَّلُوا أَعْبَاءَ الْمَغَارِمِ تُحْرِزُوا قَصَبَاتِ الْمَغَانِمِ","enWisdom":"Work hard to acquire noble traits and bear the burden of [others’] liabilities, [as a result] you will achieve the greatest gains","Qsm":"3","Bab":"13","Fsl":"84","Topic":"525","Source":"1","fav":0,"lastcheckdate":""},{"_id":7326,"BookId":7326,"Wisdom":"اكْتِسَابُ الْحَسَنَاتِ مِنْ أَفْضَلِ الْمَكَاسِبِ","enWisdom":"Acquiring of good deeds is one of the best of earnings","Qsm":"3","Bab":"13","Fsl":"84","Topic":"525","Source":"1","fav":0,"lastcheckdate":""},{"_id":7327,"BookId":7327,"Wisdom":"رُوحُوا فِي الْمَكَارِمِ وَادَّلِجُوا فِي حَاجَةِ مَنْ‏ هُوَ نَائِمٌ","enWisdom":"End your day’s work with noble deeds and begin the night by fulfilling the needs of the one who is asleep [and unaware of your assistance]","Qsm":"3","Bab":"13","Fsl":"84","Topic":"525","Source":"1","fav":0,"lastcheckdate":""},{"_id":7328,"BookId":7328,"Wisdom":"ظَرْفُ الْمُؤْمِنِ نَزَاهَتُهُ عَنِ الْمَحَارِمِ وَمُبَادَرَتُهُ إِلَى الْمَكَارِمِ","enWisdom":"The integrity of a believer is in his keeping away from what is forbidden and hastening towards virtues","Qsm":"3","Bab":"13","Fsl":"84","Topic":"525","Source":"1","fav":0,"lastcheckdate":""},{"_id":7329,"BookId":7329,"Wisdom":"كُنْ مُتَّصِفاً بِالْفَضَائِلِ مُتَبَرِّئاً مِنَ الرَّذَائِلِ","enWisdom":"Become distinguished by virtues and renounce vices","Qsm":"3","Bab":"13","Fsl":"84","Topic":"525","Source":"1","fav":0,"lastcheckdate":""},{"_id":7330,"BookId":7330,"Wisdom":"كَمَالُ الْفَضَائِلِ شَرَفُ الْخَلَائِقِ","enWisdom":"The perfection of virtues is [in] honourable qualities","Qsm":"3","Bab":"13","Fsl":"84","Topic":"525","Source":"1","fav":0,"lastcheckdate":""},{"_id":7331,"BookId":7331,"Wisdom":"مَنْ كَثُرَتْ عَوَارِفُهُ كَثُرَتْ مَعَارِفُهُ","enWisdom":"One whose empathy (or kind acts) increases, his acquaintances increases","Qsm":"3","Bab":"13","Fsl":"84","Topic":"525","Source":"1","fav":0,"lastcheckdate":""},{"_id":7332,"BookId":7332,"Wisdom":"مَنْ قَلَّتْ فَضَائِلُهُ ضَعُفَتْ وَسَائِلُهُ","enWisdom":"One whose merits are few, his means are weak","Qsm":"3","Bab":"13","Fsl":"84","Topic":"525","Source":"1","fav":0,"lastcheckdate":""},{"_id":7333,"BookId":7333,"Wisdom":"مِنْ كَمَالِ الشَّرَفِ الْأَخْذُ بِجَامِعِ الْفَضْلِ","enWisdom":"Holding on to comprehensive merit (or merits) is from the perfection of honour","Qsm":"3","Bab":"13","Fsl":"84","Topic":"525","Source":"1","fav":0,"lastcheckdate":""},{"_id":7334,"BookId":7334,"Wisdom":"مِنْ أَحْسَنِ الْمَكَارِمِ بَثُّ الْمَعْرُوفِ","enWisdom":"One of the best noble deeds is spreading goodness [and virtue]","Qsm":"3","Bab":"13","Fsl":"84","Topic":"525","Source":"1","fav":0,"lastcheckdate":""},{"_id":7335,"BookId":7335,"Wisdom":"مِنْ أَحْسَنِ الْمَكَارِمِ تَجَنُّبُ الْمَحَارِمِ","enWisdom":"One of the best noble deeds is keeping away from the forbidden","Qsm":"3","Bab":"13","Fsl":"84","Topic":"525","Source":"1","fav":0,"lastcheckdate":""},{"_id":7336,"BookId":7336,"Wisdom":"نَيْلُ الْمَآثِرِ بِبَذْلِ الْمَكَارِمِ","enWisdom":"Achievement of glorious feats is through performing noble deeds","Qsm":"3","Bab":"13","Fsl":"84","Topic":"525","Source":"1","fav":0,"lastcheckdate":""}]