[{"_id":9125,"BookId":9125,"Wisdom":"الصَّدَقَةُ كَنْزٌ","enWisdom":"Charity is a treasure","Qsm":"5","Bab":"19","Fsl":"136","Topic":"627","Source":"1","fav":0,"lastcheckdate":""},{"_id":9126,"BookId":9126,"Wisdom":"الصَّدَقَةُ تَقِي [تَفِي‏ءُ]","enWisdom":"Charity protects","Qsm":"5","Bab":"19","Fsl":"136","Topic":"627","Source":"1","fav":0,"lastcheckdate":""},{"_id":9127,"BookId":9127,"Wisdom":"الصَّدَقَةُ أَفْضَلُ الْقُرَبِ","enWisdom":"Charity is the best means of attaining closeness [to Allah]","Qsm":"5","Bab":"19","Fsl":"136","Topic":"627","Source":"1","fav":0,"lastcheckdate":""},{"_id":9128,"BookId":9128,"Wisdom":"الصَّدَقَةُ أَفْضَلُ الْحَسَنَاتِ","enWisdom":"Charity is the best of virtuous deeds","Qsm":"5","Bab":"19","Fsl":"136","Topic":"627","Source":"1","fav":0,"lastcheckdate":""},{"_id":9129,"BookId":9129,"Wisdom":"الصَّدَقَةُ كَنْزُ الْمُوسِرِ","enWisdom":"Charity is a valuable treasure","Qsm":"5","Bab":"19","Fsl":"136","Topic":"627","Source":"1","fav":0,"lastcheckdate":""},{"_id":9130,"BookId":9130,"Wisdom":"الصَّدَقَةُ تَقِي مَصَارِعَ السَّوْءِ","enWisdom":"Charity protects one from falling into evil","Qsm":"5","Bab":"19","Fsl":"136","Topic":"627","Source":"1","fav":0,"lastcheckdate":""},{"_id":9131,"BookId":9131,"Wisdom":"الصَّدَقَةُ فِي السِّرِّ مِنْ أَفْضَلِ الْبِرِّ","enWisdom":"Charity given secretly is from the best righteous actions","Qsm":"5","Bab":"19","Fsl":"136","Topic":"627","Source":"1","fav":0,"lastcheckdate":""},{"_id":9132,"BookId":9132,"Wisdom":"الصَّدَقَةُ أَعْظَمُ الرِّبْحَيْنِ","enWisdom":"harity is the greater of the two gains","Qsm":"5","Bab":"19","Fsl":"136","Topic":"627","Source":"1","fav":0,"lastcheckdate":""},{"_id":9133,"BookId":9133,"Wisdom":"الصَّدَقَةُ أَفْضَلُ الذُّخْرَيْنِ","enWisdom":"Charity is the better of the two reserves","Qsm":"5","Bab":"19","Fsl":"136","Topic":"627","Source":"1","fav":0,"lastcheckdate":""},{"_id":9134,"BookId":9134,"Wisdom":"الصَّدَقَةُ تَسْتَنْزِلُ [تُنْزِلُ‏] الرَّحْمَةَ","enWisdom":"Charity brings down mercy","Qsm":"5","Bab":"19","Fsl":"136","Topic":"627","Source":"1","fav":0,"lastcheckdate":""},{"_id":9135,"BookId":9135,"Wisdom":"الصَّدَقَةُ تَسْتَدْفِعُ الْبَلَاءَ وَالنَّقِمَةَ","enWisdom":"Charity repels tribulation and calamity","Qsm":"5","Bab":"19","Fsl":"136","Topic":"627","Source":"1","fav":0,"lastcheckdate":""},{"_id":9136,"BookId":9136,"Wisdom":"اسْتَنْزِلُوا الرِّزْقَ بِالصَّدَقَةِ","enWisdom":"Make sustenance come down by [giving] charity","Qsm":"5","Bab":"19","Fsl":"136","Topic":"627","Source":"1","fav":0,"lastcheckdate":""},{"_id":9137,"BookId":9137,"Wisdom":"إِنَّ أَفْضَلَ الْخَيْرِ صَدَقَةُ السِّرِّ وَبِرُّ الْوَالِدَيْنِ وَصِلَةُ الرَّحِمِ","enWisdom":"Indeed the best of good deeds are giving charity anonymously, being good with your parents and keeping ties with near relations","Qsm":"5","Bab":"19","Fsl":"136","Topic":"627","Source":"1","fav":0,"lastcheckdate":""},{"_id":9138,"BookId":9138,"Wisdom":"إِذَا رُزِقْتَ فَأَنْفِقْ","enWisdom":"When you are blessed with sustenance then give charity","Qsm":"5","Bab":"19","Fsl":"136","Topic":"627","Source":"1","fav":0,"lastcheckdate":""},{"_id":9139,"BookId":9139,"Wisdom":"إِذَا أَمْلَقْتُمْ فَتَاجِرُوا اللَّهَ بِالصَّدَقَةِ","enWisdom":"When you become penniless then do business with Allah through charity","Qsm":"5","Bab":"19","Fsl":"136","Topic":"627","Source":"1","fav":0,"lastcheckdate":""},{"_id":9140,"BookId":9140,"Wisdom":"إِذَا قَدَّمْتَ مَالَكَ لِآخِرَتِكَ وَاسْتَخْلَفْتَ اللَّهَ سُبْحَانَهُ عَلَى مَنْ خَلَّفْتَهُ مِنْ بَعْدِكَ سَعِدْتَ بِمَا قَدَّمْتَ وَأَحْسَنَ اللَّهُ لَكَ الْخِلَافَةَ عَلَى مَنْ خَلَّفْتَ","enWisdom":"When you send forth your wealth for your Hereafter and leave [the affair of] your heirs in the hands of Allah, you will be felicitous by that which you have forwarded and Allah will take good care of those whom you leave behind","Qsm":"5","Bab":"19","Fsl":"136","Topic":"627","Source":"1","fav":0,"lastcheckdate":""},{"_id":9141,"BookId":9141,"Wisdom":"بِالصَّدَقَةِ تَفْسُحُ الْآجَالُ","enWisdom":"Through charity, death gets deferred","Qsm":"5","Bab":"19","Fsl":"136","Topic":"627","Source":"1","fav":0,"lastcheckdate":""},{"_id":9142,"BookId":9142,"Wisdom":"بَرَكَةُ الْمَالِ فِي الصَّدَقَةِ","enWisdom":"The blessing of wealth is in charity","Qsm":"5","Bab":"19","Fsl":"136","Topic":"627","Source":"1","fav":0,"lastcheckdate":""},{"_id":9143,"BookId":9143,"Wisdom":"ثَقِّلُوا مَوَازِينَكُمْ بِالصَّدَقَةِ","enWisdom":"Make your weights [of good deeds] heavy with charity","Qsm":"5","Bab":"19","Fsl":"136","Topic":"627","Source":"1","fav":0,"lastcheckdate":""},{"_id":9144,"BookId":9144,"Wisdom":"حَصِّنُوا أَنْفُسَكُمْ بِالصَّدَقَةِ","enWisdom":"Safeguard yourselves through charity","Qsm":"5","Bab":"19","Fsl":"136","Topic":"627","Source":"1","fav":0,"lastcheckdate":""},{"_id":9145,"BookId":9145,"Wisdom":"خَيْرُ الصَّدَقَةِ أَخْفَاهَا","enWisdom":"The best charity is that which is given most secretly","Qsm":"5","Bab":"19","Fsl":"136","Topic":"627","Source":"1","fav":0,"lastcheckdate":""},{"_id":9146,"BookId":9146,"Wisdom":"دِرْهَمُ الْفَقِيرِ أَزْكَى عِنْدَ اللَّهِ مِنْ دِينَارِ الْغَنِيِّ","enWisdom":"The dirham of a poor man is purer in the sight of Allah than the dinar of the rich","Qsm":"5","Bab":"19","Fsl":"136","Topic":"627","Source":"1","fav":0,"lastcheckdate":""},{"_id":9147,"BookId":9147,"Wisdom":"سُوسُوا إِيمَانَكُمْ بِالصَّدَقَةِ","enWisdom":"Foster your faith with charity","Qsm":"5","Bab":"19","Fsl":"136","Topic":"627","Source":"1","fav":0,"lastcheckdate":""},{"_id":9148,"BookId":9148,"Wisdom":"سُوسُوا أَنْفُسَكُمْ بِالْوَرَعِ وَدَاوُوا مَرْضَاكُمْ بِالصَّدَقَةِ","enWisdom":"Groom yourselves with piety and cure your sick with charity","Qsm":"5","Bab":"19","Fsl":"136","Topic":"627","Source":"1","fav":0,"lastcheckdate":""},{"_id":9149,"BookId":9149,"Wisdom":"صَدَقَةُ السِّرِّ تُكَفِّرُ الْخَطِيئَةَ وَصَدَقَةُ الْعَلَانِيَةِ مَثْرَاةٌ فِي الْمَالِ","enWisdom":"Charity given in secret expiates wrongdoings and charity given openly is a means of increasing wealth","Qsm":"5","Bab":"19","Fsl":"136","Topic":"627","Source":"1","fav":0,"lastcheckdate":""},{"_id":9150,"BookId":9150,"Wisdom":"صَدَقَةُ الْعَلَانِيَةِ تَدْفَعُ مِيتَةَ السَّوْءِ","enWisdom":"Charity given openly repels ill-fated death","Qsm":"5","Bab":"19","Fsl":"136","Topic":"627","Source":"1","fav":0,"lastcheckdate":""},{"_id":9151,"BookId":9151,"Wisdom":"عَلَيْكَ بِالصَّدَقَةِ تَنْجُ مِنْ دَنَاءَةِ الشُّحِّ","enWisdom":"Give charity and you will be saved from the vileness of parsimony","Qsm":"5","Bab":"19","Fsl":"136","Topic":"627","Source":"1","fav":0,"lastcheckdate":""},{"_id":9152,"BookId":9152,"Wisdom":"كَفِّرُوا ذُنُوبَكُمْ وَتَحَبَّبُوا إِلَى رَبِّكُمْ بِالصَّدَقَةِ وَصِلَةِ الرَّحِمِ","enWisdom":"Expiate your sins and endear yourselves to your Lord through charity and keeping ties with your near relatives","Qsm":"5","Bab":"19","Fsl":"136","Topic":"627","Source":"1","fav":0,"lastcheckdate":""}]