[{"_id":9500,"BookId":9500,"Wisdom":"أَشْفَقُ النَّاسِ عَلَيْكَ أَعْوَنُهُمْ لَكَ عَلَى صَلَاحِ نَفْسِكَ وَأَنْصَحُهُمْ لَكَ فِي دِينِكَ","enWisdom":"The person who is most concerned about you is the one who is most helpful to you in improving [and reforming] yourself and is most sincere in advising you with regards to your religion","Qsm":"6","Bab":"21","Fsl":"148","Topic":"646","Source":"1","fav":0,"lastcheckdate":""},{"_id":9501,"BookId":9501,"Wisdom":"خَيْرُ الْإِخْوَانِ أَقَلُّهُمْ مُصَانَعَةً فِي النَّصِيحَةِ","enWisdom":"Good brotherhood increases reward and beautifies praise","Qsm":"6","Bab":"21","Fsl":"148","Topic":"646","Source":"1","fav":0,"lastcheckdate":""},{"_id":9502,"BookId":9502,"Wisdom":"خَيْرُ الْإِخْوَانِ أَنْصَحُهُمْ وَشَرُّهُمْ أَغَشُّهُمْ","enWisdom":"The best of brothers are the most sincere [of them] and the worst of them are the most Deceitful","Qsm":"6","Bab":"21","Fsl":"148","Topic":"646","Source":"1","fav":0,"lastcheckdate":""},{"_id":9503,"BookId":9503,"Wisdom":"لِيَكُنْ أَحَبُّ النَّاسِ إِلَيْكَ الْمُشْفِقَ النَّاصِحَ","enWisdom":"Let the most beloved person to you be the compassionate adviser","Qsm":"6","Bab":"21","Fsl":"148","Topic":"646","Source":"1","fav":0,"lastcheckdate":""},{"_id":9504,"BookId":9504,"Wisdom":"مَنْ صَدَّقَكَ فِي نَفْسِكَ فَقَدْ أَرْشَدَكَ","enWisdom":"One who is truthful to you about yourself has indeed guided you aright","Qsm":"6","Bab":"21","Fsl":"148","Topic":"646","Source":"1","fav":0,"lastcheckdate":""},{"_id":9505,"BookId":9505,"Wisdom":"مَنْ نَصَحَكَ فَقَدْ أَنْجَدَكَ","enWisdom":"Whoever gives you sincere advice has indeed helped you","Qsm":"6","Bab":"21","Fsl":"148","Topic":"646","Source":"1","fav":0,"lastcheckdate":""},{"_id":9506,"BookId":9506,"Wisdom":"مَنْ لَمْ يَنْصَحْكَ فِي صَدَاقَتِهِ فَلَا تَعْذِرْهُ","enWisdom":"One whose friendship does not benefit you, his enmity will harm you","Qsm":"6","Bab":"21","Fsl":"148","Topic":"646","Source":"1","fav":0,"lastcheckdate":""},{"_id":9507,"BookId":9507,"Wisdom":"لَا شَفِيقَ كَالْوَدُودِ النَّاصِحِ","enWisdom":"No one shows compassion like the sincere friend","Qsm":"6","Bab":"21","Fsl":"148","Topic":"646","Source":"1","fav":0,"lastcheckdate":""}]